mind_geometry/__init__.py
mind_geometry/areas.py
mind_geometry/factory.py
mind_geometry/figures.py
mind_geometry-0.0.1.dist-info/METADATA
mind_geometry-0.0.1.dist-info/WHEEL
mind_geometry-0.0.1.dist-info/licenses/LICENSE
mind_geometry-0.0.1.dist-info/RECORD
